omoide_client/__init__.py
omoide_client/client.py
omoide_client/errors.py
omoide_client/py.typed
omoide_client/types.py
omoide_client/api/__init__.py
omoide_client/api/actions/__init__.py
omoide_client/api/actions/api_action_copy_image_v1_actions_copy_image_source_item_uuid_to_target_item_uuid_post.py
omoide_client/api/actions/api_action_rebuild_computed_tags_v1_actions_rebuild_computed_tags_item_uuid_post.py
omoide_client/api/actions/api_action_rebuild_known_tags_for_all_v1_actions_rebuild_known_tags_for_all_post.py
omoide_client/api/actions/api_action_rebuild_known_tags_for_anon_v1_actions_rebuild_known_tags_for_anon_post.py
omoide_client/api/actions/api_action_rebuild_known_tags_for_user_v1_actions_rebuild_known_tags_for_user_user_uuid_post.py
omoide_client/api/browse/__init__.py
omoide_client/api/browse/api_browse_v1_browse_item_uuid_get.py
omoide_client/api/exif/__init__.py
omoide_client/api/exif/api_create_exif_v1_exif_item_uuid_post.py
omoide_client/api/exif/api_delete_exif_v1_exif_item_uuid_delete.py
omoide_client/api/exif/api_read_exif_v1_exif_item_uuid_get.py
omoide_client/api/exif/api_update_exif_v1_exif_item_uuid_put.py
omoide_client/api/home/__init__.py
omoide_client/api/home/api_home_v1_home_get.py
omoide_client/api/info/__init__.py
omoide_client/api/info/api_get_myself_v1_info_whoami_get.py
omoide_client/api/info/api_get_version_v1_info_version_get.py
omoide_client/api/items/__init__.py
omoide_client/api/items/api_change_parent_item_v1_items_item_uuid_parent_new_parent_uuid_put.py
omoide_client/api/items/api_create_item_v1_items_post.py
omoide_client/api/items/api_create_many_items_v1_items_bulk_post.py
omoide_client/api/items/api_delete_item_v1_items_item_uuid_delete.py
omoide_client/api/items/api_download_collection_v1_items_download_item_uuid_get.py
omoide_client/api/items/api_get_item_v1_items_item_uuid_get.py
omoide_client/api/items/api_get_many_items_v1_items_get.py
omoide_client-0.3.12.dist-info/licenses/LICENSE
omoide_client-0.3.12.dist-info/METADATA
omoide_client-0.3.12.dist-info/WHEEL
omoide_client-0.3.12.dist-info/top_level.txt
omoide_client-0.3.12.dist-info/RECORD
