Metadata-Version: 2.4
Name: omoide-client
Version: 0.3.12
Summary: Python client for Omoide service
Requires-Python: >=3.10
License-File: LICENSE
Dynamic: license-file
